seismicutils/__init__.py
seismicutils/calculus.py
seismicutils/records.py
seismicutils/spectrum.py
seismicutils-1.0.0.dist-info/LICENSE
seismicutils-1.0.0.dist-info/METADATA
seismicutils-1.0.0.dist-info/WHEEL
seismicutils-1.0.0.dist-info/RECORD
